AUTHORS
LICENSE
MANIFEST.in
README.rst
setup.py
collage/__init__.py
collage/templatetags/__init__.py
collage/templatetags/bricks.py
collage/templatetags/collage.py
collage/templatetags/settings.py
django_collage.egg-info/PKG-INFO
django_collage.egg-info/SOURCES.txt
django_collage.egg-info/dependency_links.txt
django_collage.egg-info/not-zip-safe
django_collage.egg-info/requires.txt
django_collage.egg-info/top_level.txt