Metadata-Version: 1.1
Name: django-collage
Version: 1.0.1
Summary: django collages
Home-page: http://github.com/gotlium/django-collage
Author: GoTLiuM InSPiRiT
Author-email: gotlium@gmail.com
License: UNKNOWN
Keywords: django collage
Platform: UNKNOWN
Classifier: Development Status :: 5 - Production/Stable
Classifier: Environment :: Web Environment
Classifier: Framework :: Django
Classifier: Intended Audience :: Developers
Classifier: License :: OSI Approved :: GNU General Public License (GPL)
Classifier: Operating System :: OS Independent
Classifier: Programming Language :: Python
